alectra/__init__.py
alectra/data/data.csv
alectra/data/vocab.txt
alectra/main.py
alectra/tools.py
alectra-0.1.0.dist-info/METADATA
alectra-0.1.0.dist-info/WHEEL
alectra-0.1.0.dist-info/RECORD
