Metadata-Version: 2.4
Name: alectra
Version: 0.1.0
Summary: Simple lightweight algorithm for accurate sentiment analysis accross a range of conversational topics.
License-Expression: MIT
Author: rasimoon
Author-email: rahsaanlink@gmail.com
Requires-Python: >=3.13
Classifier: Programming Language :: Python :: 3
Classifier: Programming Language :: Python :: 3.13
Classifier: Programming Language :: Python :: 3.14
Requires-Dist: numpy (>=2.3.3)
Requires-Dist: onnxruntime (>=1.23.0)
Requires-Dist: pandas (>=2.3.2)
Requires-Dist: tokenizers (>=0.22.1)
